[{"type":"constructor","inputs":[{"name":"registry","type":"address"}],"stateMutability":"nonpayable"},{"type":"function","name":"registry","inputs":[],"outputs":[{"name":"","type":"address"}],"stateMutability":"view"},{"type":"function","name":"setDisplayName","inputs":[{"name":"name","type":"string"}],"outputs":[],"stateMutability":"nonpayable"},{"type":"function","name":"createGameWithNonce","inputs":[{"name":"pack_id","type":"uint32"},{"name":"num_questions","type":"uint8"},{"name":"answer_blocks","type":"uint32"},{"name":"review_blocks","type":"uint32"},{"name":"max_players","type":"uint8"},{"name":"creation_nonce","type":"uint64"}],"outputs":[],"stateMutability":"nonpayable"},{"type":"function","name":"joinGame","inputs":[{"name":"game_id","type":"uint64"}],"outputs":[],"stateMutability":"nonpayable"},{"type":"function","name":"leaveLobby","inputs":[{"name":"game_id","type":"uint64"}],"outputs":[],"stateMutability":"nonpayable"},{"type":"function","name":"startGame","inputs":[{"name":"game_id","type":"uint64"}],"outputs":[],"stateMutability":"nonpayable"},{"type":"function","name":"submitAnswer","inputs":[{"name":"game_id","type":"uint64"},{"name":"answer","type":"string"},{"name":"wager","type":"uint32"}],"outputs":[],"stateMutability":"nonpayable"},{"type":"function","name":"voteCorrect","inputs":[{"name":"game_id","type":"uint64"},{"name":"target","type":"address"}],"outputs":[],"stateMutability":"nonpayable"},{"type":"function","name":"readyContinue","inputs":[{"name":"game_id","type":"uint64"}],"outputs":[],"stateMutability":"nonpayable"},{"type":"function","name":"voteDifficulty","inputs":[{"name":"game_id","type":"uint64"},{"name":"difficulty","type":"uint8"}],"outputs":[],"stateMutability":"nonpayable"},{"type":"function","name":"forfeitGame","inputs":[{"name":"game_id","type":"uint64"}],"outputs":[],"stateMutability":"nonpayable"},{"type":"function","name":"gameCount","inputs":[],"outputs":[{"name":"","type":"uint64"}],"stateMutability":"view"},{"type":"function","name":"getGameForCreation","inputs":[{"name":"who","type":"address"},{"name":"creation_nonce","type":"uint64"}],"outputs":[{"name":"","type":"uint64"}],"stateMutability":"view"},{"type":"function","name":"getGame","inputs":[{"name":"game_id","type":"uint64"}],"outputs":[{"name":"","type":"tuple","components":[{"name":"pack_id","type":"uint32"},{"name":"creator","type":"address"},{"name":"num_questions","type":"uint8"},{"name":"answer_blocks","type":"uint32"},{"name":"review_blocks","type":"uint32"},{"name":"max_players","type":"uint8"},{"name":"player_count","type":"uint8"},{"name":"active_player_count","type":"uint8"}]}],"stateMutability":"view"},{"type":"function","name":"getPhase","inputs":[{"name":"game_id","type":"uint64"}],"outputs":[{"name":"","type":"tuple","components":[{"name":"stage","type":"uint8"},{"name":"cursor","type":"uint8"},{"name":"deadline","type":"uint64"},{"name":"current_block","type":"uint64"},{"name":"final_difficulty","type":"uint8"},{"name":"slot","type":"uint8"},{"name":"submit_count","type":"uint32"},{"name":"continue_count","type":"uint32"},{"name":"player_count","type":"uint8"},{"name":"active_player_count","type":"uint8"}]}],"stateMutability":"view"},{"type":"function","name":"getPlayers","inputs":[{"name":"game_id","type":"uint64"}],"outputs":[{"name":"","type":"address[]"}],"stateMutability":"view"},{"type":"function","name":"getScores","inputs":[{"name":"game_id","type":"uint64"}],"outputs":[{"name":"","type":"uint32[]"}],"stateMutability":"view"},{"type":"function","name":"getPlayerNames","inputs":[{"name":"game_id","type":"uint64"}],"outputs":[{"name":"","type":"string[]"}],"stateMutability":"view"},{"type":"function","name":"getLiveGame","inputs":[{"name":"game_id","type":"uint64"}],"outputs":[{"name":"","type":"tuple","components":[{"name":"pack_id","type":"uint32"},{"name":"creator","type":"address"},{"name":"num_questions","type":"uint8"},{"name":"answer_blocks","type":"uint32"},{"name":"review_blocks","type":"uint32"},{"name":"max_players","type":"uint8"},{"name":"stage","type":"uint8"},{"name":"cursor","type":"uint8"},{"name":"deadline","type":"uint64"},{"name":"current_block","type":"uint64"},{"name":"final_difficulty","type":"uint8"},{"name":"slot","type":"uint8"},{"name":"submit_count","type":"uint32"},{"name":"continue_count","type":"uint32"},{"name":"player_count","type":"uint8"},{"name":"active_player_count","type":"uint8"},{"name":"players","type":"address[]"},{"name":"scores","type":"uint32[]"},{"name":"player_names","type":"string[]"},{"name":"submissions","type":"tuple[]","components":[{"name":"player","type":"address"},{"name":"submitted","type":"bool"},{"name":"answer","type":"string"},{"name":"wager","type":"uint32"},{"name":"correct","type":"bool"},{"name":"overturn_votes","type":"uint32"},{"name":"continue_ready","type":"bool"},{"name":"active","type":"bool"}]}]}],"stateMutability":"view"},{"type":"function","name":"isPlayerActive","inputs":[{"name":"game_id","type":"uint64"},{"name":"who","type":"address"}],"outputs":[{"name":"","type":"bool"}],"stateMutability":"view"},{"type":"function","name":"getSubmissions","inputs":[{"name":"game_id","type":"uint64"},{"name":"question_key","type":"uint8"}],"outputs":[{"name":"","type":"tuple[]","components":[{"name":"player","type":"address"},{"name":"submitted","type":"bool"},{"name":"answer","type":"string"},{"name":"wager","type":"uint32"},{"name":"correct","type":"bool"},{"name":"overturn_votes","type":"uint32"},{"name":"continue_ready","type":"bool"},{"name":"active","type":"bool"}]}],"stateMutability":"view"}]